pelican/plugins/pelican_pagination/__init__.py
pelican_pagination-2.0.1.post1.dist-info/METADATA
pelican_pagination-2.0.1.post1.dist-info/WHEEL
pelican_pagination-2.0.1.post1.dist-info/licenses/LICENSE
pelican_pagination-2.0.1.post1.dist-info/RECORD
