Metadata-Version: 2.1
Name: pelican-pagination
Version: 2.0.1.post1
Summary: Paginate articles
Keywords: pelican plugin pagination
Author-Email: Bryan Weber <bryan.w.weber@gmail.com>
License: BSD-3-Clause
Classifier: Development Status :: 5 - Production/Stable
Classifier: Environment :: Console
Classifier: Framework :: Pelican
Classifier: Framework :: Pelican :: Plugins
Classifier: Intended Audience :: End Users/Desktop
Classifier: License :: OSI Approved :: BSD License
Classifier: Operating System :: OS Independent
Classifier: Programming Language :: Python :: 3
Classifier: Programming Language :: Python :: 3.8
Classifier: Programming Language :: Python :: 3.9
Classifier: Programming Language :: Python :: 3.10
Classifier: Programming Language :: Python :: 3.11
Classifier: Programming Language :: Python :: 3.12
Classifier: Topic :: Internet :: WWW/HTTP
Classifier: Topic :: Software Development :: Libraries :: Python Modules
Project-URL: Homepage, https://github.com/bryanwweber/pelican-pagination
Project-URL: Source, https://github.com/bryanwweber/pelican-pagination
Project-URL: Documentation, https://docs.getpelican.com
Project-URL: Funding, https://donate.getpelican.com/
Project-URL: Issues, https://github.com/bryanwweber/pelican-pagination/issues
Requires-Python: <4.0,>=3.8.1
Requires-Dist: pelican>=4.5
